{
  "cnt_einsaetze": 3,
  "cnt_feuerwehren": 3,
  "einsaetze": [
    {
      "einsatz": {
        "adresse": {
          "default": "Laakirchen",
          "earea": "Laakirchen",
          "ecompl": "",
          "efeanme": "",
          "emun": "Laakirchen",
          "estnum": ""
        },
        "alarmstufe": "0",
        "bezirk": {
          "id": 3,
          "text": "Gmunden"
        },
        "cntfeuerwehren": 1,
        "einsatzart": "SELBST",
        "einsatzort": "GM - Laakirchen",
        "einsatzsubtyp": {
          "id": "TETRA-SELBST",
          "text": "Einsatz od. Einsatzübung"
        },
        "einsatztyp": {
          "id": "SELBST",
          "text": "Selbstständiger Einsatz"
        },
        "feuerwehren": {
          "403262": {
            "feuerwehr": "Feuerwehr/Florian Steyrermühl Ag (36262)"
          }
        },
        "feuerwehrenarray": {
          "0": {
            "fwname": "Feuerwehr/Florian Steyrermühl Ag (36262)",
            "fwnr": 403262
          }
        },
        "inzeit": "",
        "num1": "E241100026",
        "startzeit": "Fri, 01 Nov 2024 13:08:52 +0100",
        "status": "offen",
        "wgs84": {
          "lat": "47.9914",
          "lng": "13.799"
        }
      }
    },
    {
      "einsatz": {
        "adresse": {
          "default": "Lembach im Mühlkreis",
          "earea": "Lembach im Mühlkreis",
          "ecompl": "",
          "efeanme": "",
          "emun": "Lembach im Mühlkreis",
          "estnum": ""
        },
        "alarmstufe": "0",
        "bezirk": {
          "id": 9,
          "text": "Rohrbach"
        },
        "cntfeuerwehren": 1,
        "einsatzart": "SELBST",
        "einsatzort": "RO - Lembach im Mühlkreis",
        "einsatzsubtyp": {
          "id": "TETRA-SELBST",
          "text": "Einsatz od. Einsatzübung"
        },
        "einsatztyp": {
          "id": "SELBST",
          "text": "Selbstständiger Einsatz"
        },
        "feuerwehren": {
          "409205": {
            "feuerwehr": "Feuerwehr/Florian Lembach im Mühlkreis (44205)"
          }
        },
        "feuerwehrenarray": {
          "0": {
            "fwname": "Feuerwehr/Florian Lembach im Mühlkreis (44205)",
            "fwnr": 409205
          }
        },
        "inzeit": "",
        "num1": "E241100024",
        "startzeit": "Fri, 01 Nov 2024 12:37:58 +0100",
        "status": "offen",
        "wgs84": {
          "lat": "48.4984",
          "lng": "13.8945"
        }
      }
    },
    {
      "einsatz": {
        "adresse": {
          "default": "Ottnang am Hausruck",
          "earea": "Ottnang am Hausruck",
          "ecompl": "",
          "efeanme": "",
          "emun": "Ottnang am Hausruck",
          "estnum": ""
        },
        "alarmstufe": "0",
        "bezirk": {
          "id": 13,
          "text": "Vöcklabruck"
        },
        "cntfeuerwehren": 1,
        "einsatzart": "SELBST",
        "einsatzort": "VB - Ottnang am Hausruck",
        "einsatzsubtyp": {
          "id": "TETRA-SELBST",
          "text": "Einsatz od. Einsatzübung"
        },
        "einsatztyp": {
          "id": "SELBST",
          "text": "Selbstständiger Einsatz"
        },
        "feuerwehren": {
          "413303": {
            "feuerwehr": "Feuerwehr/Florian Bruckmühl (50303)"
          }
        },
        "feuerwehrenarray": {
          "0": {
            "fwname": "Feuerwehr/Florian Bruckmühl (50303)",
            "fwnr": 413303
          }
        },
        "inzeit": "",
        "num1": "E241100023",
        "startzeit": "Fri, 01 Nov 2024 12:14:46 +0100",
        "status": "offen",
        "wgs84": {
          "lat": "48.1045",
          "lng": "13.6226"
        }
      }
    }
  ],
  "title": "laufend",
  "version": "1.3.1",
  "webext2": true
}
