{
  "cnt_einsaetze": 1,
  "cnt_feuerwehren": 3,
  "einsaetze": [
    {
      "einsatz": {
        "adresse": {
          "default": "BAD ISCHL",
          "earea": "",
          "ecompl": "FW PFANDL",
          "efeanme": "",
          "emun": "BAD ISCHL",
          "estnum": ""
        },
        "alarmstufe": 1,
        "bezirk": {
          "id": 3,
          "text": "Gmunden"
        },
        "cntfeuerwehren": 3,
        "einsatzart": "TEE",
        "einsatzort": "GM - BAD ISCHL",
        "einsatzsubtyp": {
          "id": "SONSTIGE-TK",
          "text": "TECHNISCHER EINSATZ KLEIN"
        },
        "einsatztyp": {
          "id": "TK",
          "text": "TECHNISCH \"KLEIN\" FEUERWEHREINSATZ"
        },
        "feuerwehren": {
          "403102": {
            "feuerwehr": "FF Bad Ischl"
          },
          "403112": {
            "feuerwehr": "FF Pfandl"
          },
          "403117": {
            "feuerwehr": "FF St. Agatha / GM"
          }
        },
        "feuerwehrenarray": {
          "0": {
            "fwname": "FF Bad Ischl",
            "fwnr": "403102"
          },
          "1": {
            "fwname": "FF Pfandl",
            "fwnr": "403112"
          },
          "2": {
            "fwname": "FF St. Agatha / GM",
            "fwnr": "403117"
          }
        },
        "inzeit": "",
        "num1": "E240100141",
        "startzeit": "Tue, 02 Jan 2024 20:41:26 +0100",
        "status": "offen",
        "wgs84": {
          "lat": 47.72039,
          "lng": 13.58323
        }
      }
    }
  ],
  "title": "laufende Einsätze",
  "version": "1.3.1",
  "webext2": true
}
