{
  "cnt_einsaetze": 28,
  "cnt_feuerwehren": 28,
  "einsaetze": [
    {
      "einsatz": {
        "adresse": {
          "default": "Straß im Attergau",
          "earea": "Straß im Attergau",
          "ecompl": "",
          "efeanme": "",
          "emun": "Straß im Attergau",
          "estnum": ""
        },
        "alarmstufe": "0",
        "bezirk": {
          "id": 13,
          "text": "Vöcklabruck"
        },
        "cntfeuerwehren": 1,
        "einsatzart": "SELBST",
        "einsatzort": "VB - Straß im Attergau",
        "einsatzsubtyp": {
          "id": "TETRA-SELBST",
          "text": "Einsatz od. Einsatzübung"
        },
        "einsatztyp": {
          "id": "SELBST",
          "text": "Selbstständiger Einsatz"
        },
        "feuerwehren": {
          "413512": {
            "feuerwehr": "Feuerwehr/Florian Kronberg (50512)"
          }
        },
        "feuerwehrenarray": {
          "0": {
            "fwname": "Feuerwehr/Florian Kronberg (50512)",
            "fwnr": 413512
          }
        },
        "inzeit": "",
        "num1": "E241003787",
        "startzeit": "Sat, 26 Oct 2024 19:12:03 +0200",
        "status": "offen",
        "wgs84": {
          "lat": "47.9003",
          "lng": "13.4879"
        }
      }
    },
    {
      "einsatz": {
        "adresse": {
          "default": "Frankenburg am Hausruck",
          "earea": "Frankenburg am Hausruck",
          "ecompl": "",
          "efeanme": "",
          "emun": "Frankenburg am Hausruck",
          "estnum": ""
        },
        "alarmstufe": "0",
        "bezirk": {
          "id": 13,
          "text": "Vöcklabruck"
        },
        "cntfeuerwehren": 1,
        "einsatzart": "SELBST",
        "einsatzort": "VB - Frankenburg am Hausruck",
        "einsatzsubtyp": {
          "id": "TETRA-SELBST",
          "text": "Einsatz od. Einsatzübung"
        },
        "einsatztyp": {
          "id": "SELBST",
          "text": "Selbstständiger Einsatz"
        },
        "feuerwehren": {
          "413104": {
            "feuerwehr": "Feuerwehr/Florian Badstuben (50104)"
          }
        },
        "feuerwehrenarray": {
          "0": {
            "fwname": "Feuerwehr/Florian Badstuben (50104)",
            "fwnr": 413104
          }
        },
        "inzeit": "",
        "num1": "E241003786",
        "startzeit": "Sat, 26 Oct 2024 19:11:02 +0200",
        "status": "offen",
        "wgs84": {
          "lat": "48.0837",
          "lng": "13.4946"
        }
      }
    },
    {
      "einsatz": {
        "adresse": {
          "default": "St. Georgen im Attergau",
          "earea": "St. Georgen im Attergau",
          "ecompl": "",
          "efeanme": "",
          "emun": "St. Georgen im Attergau",
          "estnum": ""
        },
        "alarmstufe": "0",
        "bezirk": {
          "id": 13,
          "text": "Vöcklabruck"
        },
        "cntfeuerwehren": 1,
        "einsatzart": "SELBST",
        "einsatzort": "VB - St. Georgen im Attergau",
        "einsatzsubtyp": {
          "id": "TETRA-SELBST",
          "text": "Einsatz od. Einsatzübung"
        },
        "einsatztyp": {
          "id": "SELBST",
          "text": "Selbstständiger Einsatz"
        },
        "feuerwehren": {
          "413518": {
            "feuerwehr": "Feuerwehr/Florian Sankt Georgen im Attergau (50518)"
          }
        },
        "feuerwehrenarray": {
          "0": {
            "fwname": "Feuerwehr/Florian Sankt Georgen im Attergau (50518)",
            "fwnr": 413518
          }
        },
        "inzeit": "",
        "num1": "E241003785",
        "startzeit": "Sat, 26 Oct 2024 19:10:42 +0200",
        "status": "offen",
        "wgs84": {
          "lat": "47.9359",
          "lng": "13.4883"
        }
      }
    },
    {
      "einsatz": {
        "adresse": {
          "default": "Straß im Attergau",
          "earea": "Straß im Attergau",
          "ecompl": "",
          "efeanme": "",
          "emun": "Straß im Attergau",
          "estnum": ""
        },
        "alarmstufe": "0",
        "bezirk": {
          "id": 13,
          "text": "Vöcklabruck"
        },
        "cntfeuerwehren": 1,
        "einsatzart": "SELBST",
        "einsatzort": "VB - Straß im Attergau",
        "einsatzsubtyp": {
          "id": "TETRA-SELBST",
          "text": "Einsatz od. Einsatzübung"
        },
        "einsatztyp": {
          "id": "SELBST",
          "text": "Selbstständiger Einsatz"
        },
        "feuerwehren": {
          "413523": {
            "feuerwehr": "Feuerwehr/Florian Strass im Attergau (50523)"
          }
        },
        "feuerwehrenarray": {
          "0": {
            "fwname": "Feuerwehr/Florian Strass im Attergau (50523)",
            "fwnr": 413523
          }
        },
        "inzeit": "",
        "num1": "E241003784",
        "startzeit": "Sat, 26 Oct 2024 19:10:14 +0200",
        "status": "offen",
        "wgs84": {
          "lat": "47.9116",
          "lng": "13.4596"
        }
      }
    },
    {
      "einsatz": {
        "adresse": {
          "default": "Taufkirchen an der Pram",
          "earea": "Taufkirchen an der Pram",
          "ecompl": "",
          "efeanme": "",
          "emun": "Taufkirchen an der Pram",
          "estnum": ""
        },
        "alarmstufe": "0",
        "bezirk": {
          "id": 10,
          "text": "Schärding"
        },
        "cntfeuerwehren": 1,
        "einsatzart": "SELBST",
        "einsatzort": "SD - Taufkirchen an der Pram",
        "einsatzsubtyp": {
          "id": "TETRA-SELBST",
          "text": "Einsatz od. Einsatzübung"
        },
        "einsatztyp": {
          "id": "SELBST",
          "text": "Selbstständiger Einsatz"
        },
        "feuerwehren": {
          "410325": {
            "feuerwehr": "Feuerwehr/Florian Taufkirchen an der Pram (45325)"
          }
        },
        "feuerwehrenarray": {
          "0": {
            "fwname": "Feuerwehr/Florian Taufkirchen an der Pram (45325)",
            "fwnr": 410325
          }
        },
        "inzeit": "",
        "num1": "E241003780",
        "startzeit": "Sat, 26 Oct 2024 19:03:48 +0200",
        "status": "offen",
        "wgs84": {
          "lat": "48.4055",
          "lng": "13.5327"
        }
      }
    },
    {
      "einsatz": {
        "adresse": {
          "default": "Taufkirchen an der Pram",
          "earea": "Taufkirchen an der Pram",
          "ecompl": "",
          "efeanme": "",
          "emun": "Taufkirchen an der Pram",
          "estnum": ""
        },
        "alarmstufe": "0",
        "bezirk": {
          "id": 10,
          "text": "Schärding"
        },
        "cntfeuerwehren": 1,
        "einsatzart": "SELBST",
        "einsatzort": "SD - Taufkirchen an der Pram",
        "einsatzsubtyp": {
          "id": "TETRA-SELBST",
          "text": "Einsatz od. Einsatzübung"
        },
        "einsatztyp": {
          "id": "SELBST",
          "text": "Selbstständiger Einsatz"
        },
        "feuerwehren": {
          "410308": {
            "feuerwehr": "Feuerwehr/Florian Höbmannsbach (45308)"
          }
        },
        "feuerwehrenarray": {
          "0": {
            "fwname": "Feuerwehr/Florian Höbmannsbach (45308)",
            "fwnr": 410308
          }
        },
        "inzeit": "",
        "num1": "E241003779",
        "startzeit": "Sat, 26 Oct 2024 19:03:26 +0200",
        "status": "offen",
        "wgs84": {
          "lat": "48.4367",
          "lng": "13.5149"
        }
      }
    },
    {
      "einsatz": {
        "adresse": {
          "default": "Taufkirchen an der Pram",
          "earea": "Taufkirchen an der Pram",
          "ecompl": "",
          "efeanme": "",
          "emun": "Taufkirchen an der Pram",
          "estnum": ""
        },
        "alarmstufe": "0",
        "bezirk": {
          "id": 10,
          "text": "Schärding"
        },
        "cntfeuerwehren": 1,
        "einsatzart": "SELBST",
        "einsatzort": "SD - Taufkirchen an der Pram",
        "einsatzsubtyp": {
          "id": "TETRA-SELBST",
          "text": "Einsatz od. Einsatzübung"
        },
        "einsatztyp": {
          "id": "SELBST",
          "text": "Selbstständiger Einsatz"
        },
        "feuerwehren": {
          "410316": {
            "feuerwehr": "Feuerwehr/Florian Pramau (45316)"
          }
        },
        "feuerwehrenarray": {
          "0": {
            "fwname": "Feuerwehr/Florian Pramau (45316)",
            "fwnr": 410316
          }
        },
        "inzeit": "",
        "num1": "E241003778",
        "startzeit": "Sat, 26 Oct 2024 19:02:47 +0200",
        "status": "offen",
        "wgs84": {
          "lat": "48.3894",
          "lng": "13.5444"
        }
      }
    },
    {
      "einsatz": {
        "adresse": {
          "default": "Attersee",
          "earea": "Attersee",
          "ecompl": "",
          "efeanme": "",
          "emun": "Attersee",
          "estnum": ""
        },
        "alarmstufe": "0",
        "bezirk": {
          "id": 13,
          "text": "Vöcklabruck"
        },
        "cntfeuerwehren": 1,
        "einsatzart": "SELBST",
        "einsatzort": "VB - Attersee",
        "einsatzsubtyp": {
          "id": "TETRA-SELBST",
          "text": "Einsatz od. Einsatzübung"
        },
        "einsatztyp": {
          "id": "SELBST",
          "text": "Selbstständiger Einsatz"
        },
        "feuerwehren": {
          "413503": {
            "feuerwehr": "Feuerwehr/Florian Attersee (50503)"
          }
        },
        "feuerwehrenarray": {
          "0": {
            "fwname": "Feuerwehr/Florian Attersee (50503)",
            "fwnr": 413503
          }
        },
        "inzeit": "",
        "num1": "E241003777",
        "startzeit": "Sat, 26 Oct 2024 19:02:02 +0200",
        "status": "offen",
        "wgs84": {
          "lat": "47.9166",
          "lng": "13.5341"
        }
      }
    },
    {
      "einsatz": {
        "adresse": {
          "default": "Taufkirchen an der Pram",
          "earea": "Taufkirchen an der Pram",
          "ecompl": "",
          "efeanme": "",
          "emun": "Taufkirchen an der Pram",
          "estnum": ""
        },
        "alarmstufe": "0",
        "bezirk": {
          "id": 10,
          "text": "Schärding"
        },
        "cntfeuerwehren": 1,
        "einsatzart": "SELBST",
        "einsatzort": "SD - Taufkirchen an der Pram",
        "einsatzsubtyp": {
          "id": "TETRA-SELBST",
          "text": "Einsatz od. Einsatzübung"
        },
        "einsatztyp": {
          "id": "SELBST",
          "text": "Selbstständiger Einsatz"
        },
        "feuerwehren": {
          "410313": {
            "feuerwehr": "Feuerwehr/Florian Laufenbach (45313)"
          }
        },
        "feuerwehrenarray": {
          "0": {
            "fwname": "Feuerwehr/Florian Laufenbach (45313)",
            "fwnr": 410313
          }
        },
        "inzeit": "",
        "num1": "E241003776",
        "startzeit": "Sat, 26 Oct 2024 19:01:55 +0200",
        "status": "offen",
        "wgs84": {
          "lat": "48.3933",
          "lng": "13.5123"
        }
      }
    },
    {
      "einsatz": {
        "adresse": {
          "default": "Taufkirchen an der Pram",
          "earea": "Taufkirchen an der Pram",
          "ecompl": "",
          "efeanme": "",
          "emun": "Taufkirchen an der Pram",
          "estnum": ""
        },
        "alarmstufe": "0",
        "bezirk": {
          "id": 10,
          "text": "Schärding"
        },
        "cntfeuerwehren": 1,
        "einsatzart": "SELBST",
        "einsatzort": "SD - Taufkirchen an der Pram",
        "einsatzsubtyp": {
          "id": "TETRA-SELBST",
          "text": "Einsatz od. Einsatzübung"
        },
        "einsatztyp": {
          "id": "SELBST",
          "text": "Selbstständiger Einsatz"
        },
        "feuerwehren": {
          "410301": {
            "feuerwehr": "Feuerwehr/Florian Brauchsdorf (45301)"
          }
        },
        "feuerwehrenarray": {
          "0": {
            "fwname": "Feuerwehr/Florian Brauchsdorf (45301)",
            "fwnr": 410301
          }
        },
        "inzeit": "",
        "num1": "E241003775",
        "startzeit": "Sat, 26 Oct 2024 19:01:55 +0200",
        "status": "offen",
        "wgs84": {
          "lat": "48.4311",
          "lng": "13.5459"
        }
      }
    },
    {
      "einsatz": {
        "adresse": {
          "default": "Bad Ischl",
          "earea": "Bad Ischl",
          "ecompl": "",
          "efeanme": "",
          "emun": "Bad Ischl",
          "estnum": ""
        },
        "alarmstufe": "0",
        "bezirk": {
          "id": 3,
          "text": "Gmunden"
        },
        "cntfeuerwehren": 1,
        "einsatzart": "TEE",
        "einsatzort": "GM - Bad Ischl",
        "einsatzsubtyp": {
          "id": "TÜRPERSEING-TE",
          "text": "Türöffnung Person eingeschlossen"
        },
        "einsatztyp": {
          "id": "T0-ÖFFNEN-TÜR",
          "text": "Türöffnung Menschenrettung"
        },
        "feuerwehren": {
          "403102": {
            "feuerwehr": "Feuerwehr/Florian Bad Ischl (36102)"
          }
        },
        "feuerwehrenarray": {
          "0": {
            "fwname": "Feuerwehr/Florian Bad Ischl (36102)",
            "fwnr": 403102
          }
        },
        "inzeit": "",
        "num1": "E241003774",
        "startzeit": "Sat, 26 Oct 2024 18:59:25 +0200",
        "status": "offen",
        "wgs84": {
          "lat": "47.7109",
          "lng": "13.6262"
        }
      }
    },
    {
      "einsatz": {
        "adresse": {
          "default": "St. Peter am Wimberg",
          "earea": "St. Peter am Wimberg",
          "ecompl": "",
          "efeanme": "",
          "emun": "St. Peter am Wimberg",
          "estnum": ""
        },
        "alarmstufe": "0",
        "bezirk": {
          "id": 9,
          "text": "Rohrbach"
        },
        "cntfeuerwehren": 1,
        "einsatzart": "SELBST",
        "einsatzort": "RO - St. Peter am Wimberg",
        "einsatzsubtyp": {
          "id": "TETRA-SELBST",
          "text": "Einsatz od. Einsatzübung"
        },
        "einsatztyp": {
          "id": "SELBST",
          "text": "Selbstständiger Einsatz"
        },
        "feuerwehren": {
          "409315": {
            "feuerwehr": "Feuerwehr/Florian Sankt Peter am Wimberg (44315)"
          }
        },
        "feuerwehrenarray": {
          "0": {
            "fwname": "Feuerwehr/Florian Sankt Peter am Wimberg (44315)",
            "fwnr": 409315
          }
        },
        "inzeit": "",
        "num1": "E241003772",
        "startzeit": "Sat, 26 Oct 2024 18:29:07 +0200",
        "status": "offen",
        "wgs84": {
          "lat": "48.5023",
          "lng": "14.0719"
        }
      }
    },
    {
      "einsatz": {
        "adresse": {
          "default": "Regau",
          "earea": "Regau",
          "ecompl": "",
          "efeanme": "",
          "emun": "Regau",
          "estnum": ""
        },
        "alarmstufe": "0",
        "bezirk": {
          "id": 13,
          "text": "Vöcklabruck"
        },
        "cntfeuerwehren": 1,
        "einsatzart": "SELBST",
        "einsatzort": "VB - Regau",
        "einsatzsubtyp": {
          "id": "TETRA-SELBST",
          "text": "Einsatz od. Einsatzübung"
        },
        "einsatztyp": {
          "id": "SELBST",
          "text": "Selbstständiger Einsatz"
        },
        "feuerwehren": {
          "413419": {
            "feuerwehr": "Feuerwehr/Florian Regau (50419)"
          }
        },
        "feuerwehrenarray": {
          "0": {
            "fwname": "Feuerwehr/Florian Regau (50419)",
            "fwnr": 413419
          }
        },
        "inzeit": "",
        "num1": "E241003771",
        "startzeit": "Sat, 26 Oct 2024 18:24:45 +0200",
        "status": "offen",
        "wgs84": {
          "lat": "47.9893",
          "lng": "13.6896"
        }
      }
    },
    {
      "einsatz": {
        "adresse": {
          "default": "Rohrbach in OÖ",
          "earea": "Rohrbach in OÖ",
          "ecompl": "",
          "efeanme": "",
          "emun": "Rohrbach in OÖ",
          "estnum": ""
        },
        "alarmstufe": "0",
        "bezirk": {
          "id": 9,
          "text": "Rohrbach"
        },
        "cntfeuerwehren": 1,
        "einsatzart": "SELBST",
        "einsatzort": "RO - Rohrbach in OÖ",
        "einsatzsubtyp": {
          "id": "TETRA-SELBST",
          "text": "Einsatz od. Einsatzübung"
        },
        "einsatztyp": {
          "id": "SELBST",
          "text": "Selbstständiger Einsatz"
        },
        "feuerwehren": {
          "409419": {
            "feuerwehr": "Feuerwehr/Florian Rohrbach im Mühlkreis (44419)"
          }
        },
        "feuerwehrenarray": {
          "0": {
            "fwname": "Feuerwehr/Florian Rohrbach im Mühlkreis (44419)",
            "fwnr": 409419
          }
        },
        "inzeit": "",
        "num1": "E241003769",
        "startzeit": "Sat, 26 Oct 2024 18:15:55 +0200",
        "status": "offen",
        "wgs84": {
          "lat": "48.5671",
          "lng": "13.9852"
        }
      }
    },
    {
      "einsatz": {
        "adresse": {
          "default": "Kopfing im Innkreis",
          "earea": "Kopfing im Innkreis",
          "ecompl": "",
          "efeanme": "",
          "emun": "Kopfing im Innkreis",
          "estnum": ""
        },
        "alarmstufe": "0",
        "bezirk": {
          "id": 10,
          "text": "Schärding"
        },
        "cntfeuerwehren": 1,
        "einsatzart": "SELBST",
        "einsatzort": "SD - Kopfing im Innkreis",
        "einsatzsubtyp": {
          "id": "TETRA-SELBST",
          "text": "Einsatz od. Einsatzübung"
        },
        "einsatztyp": {
          "id": "SELBST",
          "text": "Selbstständiger Einsatz"
        },
        "feuerwehren": {
          "410110": {
            "feuerwehr": "Feuerwehr/Florian Kopfing im Innkreis (45110)"
          }
        },
        "feuerwehrenarray": {
          "0": {
            "fwname": "Feuerwehr/Florian Kopfing im Innkreis (45110)",
            "fwnr": 410110
          }
        },
        "inzeit": "",
        "num1": "E241003738",
        "startzeit": "Sat, 26 Oct 2024 14:02:17 +0200",
        "status": "offen",
        "wgs84": {
          "lat": "48.4433",
          "lng": "13.659"
        }
      }
    },
    {
      "einsatz": {
        "adresse": {
          "default": "Oberschlierbach",
          "earea": "Oberschlierbach",
          "ecompl": "",
          "efeanme": "",
          "emun": "Oberschlierbach",
          "estnum": ""
        },
        "alarmstufe": "0",
        "bezirk": {
          "id": 5,
          "text": "Kirchdorf"
        },
        "cntfeuerwehren": 1,
        "einsatzart": "SELBST",
        "einsatzort": "KI - Oberschlierbach",
        "einsatzsubtyp": {
          "id": "TETRA-SELBST",
          "text": "Einsatz od. Einsatzübung"
        },
        "einsatztyp": {
          "id": "SELBST",
          "text": "Selbstständiger Einsatz"
        },
        "feuerwehren": {
          "405210": {
            "feuerwehr": "Feuerwehr/Florian Oberschlierbach (38210)"
          }
        },
        "feuerwehrenarray": {
          "0": {
            "fwname": "Feuerwehr/Florian Oberschlierbach (38210)",
            "fwnr": 405210
          }
        },
        "inzeit": "",
        "num1": "E241003733",
        "startzeit": "Sat, 26 Oct 2024 14:01:29 +0200",
        "status": "offen",
        "wgs84": {
          "lat": "47.9351",
          "lng": "14.1787"
        }
      }
    },
    {
      "einsatz": {
        "adresse": {
          "default": "Kirchheim im Innkreis",
          "earea": "Kirchheim im Innkreis",
          "ecompl": "",
          "efeanme": "",
          "emun": "Kirchheim im Innkreis",
          "estnum": ""
        },
        "alarmstufe": "0",
        "bezirk": {
          "id": 8,
          "text": "Ried im Innkreis"
        },
        "cntfeuerwehren": 1,
        "einsatzart": "SELBST",
        "einsatzort": "RI - Kirchheim im Innkreis",
        "einsatzsubtyp": {
          "id": "TETRA-SELBST",
          "text": "Einsatz od. Einsatzübung"
        },
        "einsatztyp": {
          "id": "SELBST",
          "text": "Selbstständiger Einsatz"
        },
        "feuerwehren": {
          "408101": {
            "feuerwehr": "Feuerwehr/Florian Ampfenham (43101)"
          }
        },
        "feuerwehrenarray": {
          "0": {
            "fwname": "Feuerwehr/Florian Ampfenham (43101)",
            "fwnr": 408101
          }
        },
        "inzeit": "",
        "num1": "E241003732",
        "startzeit": "Sat, 26 Oct 2024 14:00:52 +0200",
        "status": "offen",
        "wgs84": {
          "lat": "48.1969",
          "lng": "13.3763"
        }
      }
    },
    {
      "einsatz": {
        "adresse": {
          "default": "Wartberg an der Krems",
          "earea": "Wartberg an der Krems",
          "ecompl": "",
          "efeanme": "",
          "emun": "Wartberg an der Krems",
          "estnum": ""
        },
        "alarmstufe": "0",
        "bezirk": {
          "id": 5,
          "text": "Kirchdorf"
        },
        "cntfeuerwehren": 1,
        "einsatzart": "SELBST",
        "einsatzort": "KI - Wartberg an der Krems",
        "einsatzsubtyp": {
          "id": "TETRA-SELBST",
          "text": "Einsatz od. Einsatzübung"
        },
        "einsatztyp": {
          "id": "SELBST",
          "text": "Selbstständiger Einsatz"
        },
        "feuerwehren": {
          "405307": {
            "feuerwehr": "Feuerwehr/Florian Strienzing (38307)"
          }
        },
        "feuerwehrenarray": {
          "0": {
            "fwname": "Feuerwehr/Florian Strienzing (38307)",
            "fwnr": 405307
          }
        },
        "inzeit": "",
        "num1": "E241003720",
        "startzeit": "Sat, 26 Oct 2024 13:32:03 +0200",
        "status": "offen",
        "wgs84": {
          "lat": "47.9794",
          "lng": "14.0795"
        }
      }
    },
    {
      "einsatz": {
        "adresse": {
          "default": "Lembach im Mühlkreis",
          "earea": "Lembach im Mühlkreis",
          "ecompl": "",
          "efeanme": "",
          "emun": "Lembach im Mühlkreis",
          "estnum": ""
        },
        "alarmstufe": "0",
        "bezirk": {
          "id": 9,
          "text": "Rohrbach"
        },
        "cntfeuerwehren": 1,
        "einsatzart": "SELBST",
        "einsatzort": "RO - Lembach im Mühlkreis",
        "einsatzsubtyp": {
          "id": "TETRA-SELBST",
          "text": "Einsatz od. Einsatzübung"
        },
        "einsatztyp": {
          "id": "SELBST",
          "text": "Selbstständiger Einsatz"
        },
        "feuerwehren": {
          "409205": {
            "feuerwehr": "Feuerwehr/Florian Lembach im Mühlkreis (44205)"
          }
        },
        "feuerwehrenarray": {
          "0": {
            "fwname": "Feuerwehr/Florian Lembach im Mühlkreis (44205)",
            "fwnr": 409205
          }
        },
        "inzeit": "",
        "num1": "E241003691",
        "startzeit": "Sat, 26 Oct 2024 09:10:52 +0200",
        "status": "offen",
        "wgs84": {
          "lat": "48.4984",
          "lng": "13.8945"
        }
      }
    },
    {
      "einsatz": {
        "adresse": {
          "default": "Laakirchen",
          "earea": "Laakirchen",
          "ecompl": "",
          "efeanme": "",
          "emun": "Laakirchen",
          "estnum": ""
        },
        "alarmstufe": "0",
        "bezirk": {
          "id": 3,
          "text": "Gmunden"
        },
        "cntfeuerwehren": 1,
        "einsatzart": "SELBST",
        "einsatzort": "GM - Laakirchen",
        "einsatzsubtyp": {
          "id": "TETRA-SELBST",
          "text": "Einsatz od. Einsatzübung"
        },
        "einsatztyp": {
          "id": "SELBST",
          "text": "Selbstständiger Einsatz"
        },
        "feuerwehren": {
          "403213": {
            "feuerwehr": "Feuerwehr/Florian Lindach (36213)"
          }
        },
        "feuerwehrenarray": {
          "0": {
            "fwname": "Feuerwehr/Florian Lindach (36213)",
            "fwnr": 403213
          }
        },
        "inzeit": "",
        "num1": "E241003689",
        "startzeit": "Sat, 26 Oct 2024 08:43:43 +0200",
        "status": "offen",
        "wgs84": {
          "lat": "47.9989",
          "lng": "13.8509"
        }
      }
    },
    {
      "einsatz": {
        "adresse": {
          "default": "Altmünster",
          "earea": "Altmünster",
          "ecompl": "",
          "efeanme": "",
          "emun": "Altmünster",
          "estnum": ""
        },
        "alarmstufe": "0",
        "bezirk": {
          "id": 3,
          "text": "Gmunden"
        },
        "cntfeuerwehren": 1,
        "einsatzart": "SELBST",
        "einsatzort": "GM - Altmünster",
        "einsatzsubtyp": {
          "id": "TETRA-SELBST",
          "text": "Einsatz od. Einsatzübung"
        },
        "einsatztyp": {
          "id": "SELBST",
          "text": "Selbstständiger Einsatz"
        },
        "feuerwehren": {
          "403214": {
            "feuerwehr": "Feuerwehr/Florian Neukirchen (36214)"
          }
        },
        "feuerwehrenarray": {
          "0": {
            "fwname": "Feuerwehr/Florian Neukirchen (36214)",
            "fwnr": 403214
          }
        },
        "inzeit": "",
        "num1": "E241003624",
        "startzeit": "Fri, 25 Oct 2024 19:06:53 +0200",
        "status": "offen",
        "wgs84": {
          "lat": "47.8738",
          "lng": "13.7073"
        }
      }
    },
    {
      "einsatz": {
        "adresse": {
          "default": "Wendling",
          "earea": "Wendling",
          "ecompl": "",
          "efeanme": "",
          "emun": "Wendling",
          "estnum": ""
        },
        "alarmstufe": "0",
        "bezirk": {
          "id": 4,
          "text": "Grieskirchen"
        },
        "cntfeuerwehren": 1,
        "einsatzart": "SELBST",
        "einsatzort": "GR - Wendling",
        "einsatzsubtyp": {
          "id": "TETRA-SELBST",
          "text": "Einsatz od. Einsatzübung"
        },
        "einsatztyp": {
          "id": "SELBST",
          "text": "Selbstständiger Einsatz"
        },
        "feuerwehren": {
          "404213": {
            "feuerwehr": "Feuerwehr/Florian Weeg (37213)"
          }
        },
        "feuerwehrenarray": {
          "0": {
            "fwname": "Feuerwehr/Florian Weeg (37213)",
            "fwnr": 404213
          }
        },
        "inzeit": "",
        "num1": "E241003619",
        "startzeit": "Fri, 25 Oct 2024 19:05:43 +0200",
        "status": "offen",
        "wgs84": {
          "lat": "48.247",
          "lng": "13.6493"
        }
      }
    },
    {
      "einsatz": {
        "adresse": {
          "default": "Neukirchen an der Vöckla",
          "earea": "Neukirchen an der Vöckla",
          "ecompl": "",
          "efeanme": "",
          "emun": "Neukirchen an der Vöckla",
          "estnum": ""
        },
        "alarmstufe": "0",
        "bezirk": {
          "id": 13,
          "text": "Vöcklabruck"
        },
        "cntfeuerwehren": 1,
        "einsatzart": "SELBST",
        "einsatzort": "VB - Neukirchen an der Vöckla",
        "einsatzsubtyp": {
          "id": "TETRA-SELBST",
          "text": "Einsatz od. Einsatzübung"
        },
        "einsatztyp": {
          "id": "SELBST",
          "text": "Selbstständiger Einsatz"
        },
        "feuerwehren": {
          "413461": {
            "feuerwehr": "Feuerwehr/Florian Brauerei Zipf (50461)"
          }
        },
        "feuerwehrenarray": {
          "0": {
            "fwname": "Feuerwehr/Florian Brauerei Zipf (50461)",
            "fwnr": 413461
          }
        },
        "inzeit": "",
        "num1": "E241003612",
        "startzeit": "Fri, 25 Oct 2024 19:03:47 +0200",
        "status": "offen",
        "wgs84": {
          "lat": "48.0375",
          "lng": "13.5026"
        }
      }
    },
    {
      "einsatz": {
        "adresse": {
          "default": "Lenzing",
          "earea": "Lenzing",
          "ecompl": "",
          "efeanme": "",
          "emun": "Lenzing",
          "estnum": ""
        },
        "alarmstufe": "0",
        "bezirk": {
          "id": 13,
          "text": "Vöcklabruck"
        },
        "cntfeuerwehren": 1,
        "einsatzart": "SELBST",
        "einsatzort": "VB - Lenzing",
        "einsatzsubtyp": {
          "id": "TETRA-SELBST",
          "text": "Einsatz od. Einsatzübung"
        },
        "einsatztyp": {
          "id": "SELBST",
          "text": "Selbstständiger Einsatz"
        },
        "feuerwehren": {
          "413420": {
            "feuerwehr": "Feuerwehr/Florian Reibersdorf (50420)"
          }
        },
        "feuerwehrenarray": {
          "0": {
            "fwname": "Feuerwehr/Florian Reibersdorf (50420)",
            "fwnr": 413420
          }
        },
        "inzeit": "",
        "num1": "E241003604",
        "startzeit": "Fri, 25 Oct 2024 19:01:41 +0200",
        "status": "offen",
        "wgs84": {
          "lat": "47.9626",
          "lng": "13.6343"
        }
      }
    },
    {
      "einsatz": {
        "adresse": {
          "default": "Pettenbach",
          "earea": "Pettenbach",
          "ecompl": "",
          "efeanme": "",
          "emun": "Pettenbach",
          "estnum": ""
        },
        "alarmstufe": "0",
        "bezirk": {
          "id": 5,
          "text": "Kirchdorf"
        },
        "cntfeuerwehren": 1,
        "einsatzart": "SELBST",
        "einsatzort": "KI - Pettenbach",
        "einsatzsubtyp": {
          "id": "TETRA-SELBST",
          "text": "Einsatz od. Einsatzübung"
        },
        "einsatztyp": {
          "id": "SELBST",
          "text": "Selbstständiger Einsatz"
        },
        "feuerwehren": {
          "405202": {
            "feuerwehr": "Feuerwehr/Florian Eggenstein (38202)"
          }
        },
        "feuerwehrenarray": {
          "0": {
            "fwname": "Feuerwehr/Florian Eggenstein (38202)",
            "fwnr": 405202
          }
        },
        "inzeit": "",
        "num1": "E241003587",
        "startzeit": "Fri, 25 Oct 2024 18:42:49 +0200",
        "status": "offen",
        "wgs84": {
          "lat": "47.9786",
          "lng": "13.9626"
        }
      }
    },
    {
      "einsatz": {
        "adresse": {
          "default": "Gampern",
          "earea": "Gampern",
          "ecompl": "",
          "efeanme": "",
          "emun": "Gampern",
          "estnum": ""
        },
        "alarmstufe": "0",
        "bezirk": {
          "id": 13,
          "text": "Vöcklabruck"
        },
        "cntfeuerwehren": 1,
        "einsatzart": "SELBST",
        "einsatzort": "VB - Gampern",
        "einsatzsubtyp": {
          "id": "TETRA-SELBST",
          "text": "Einsatz od. Einsatzübung"
        },
        "einsatztyp": {
          "id": "SELBST",
          "text": "Selbstständiger Einsatz"
        },
        "feuerwehren": {
          "413407": {
            "feuerwehr": "Feuerwehr/Florian Baumgarting (50407)"
          }
        },
        "feuerwehrenarray": {
          "0": {
            "fwname": "Feuerwehr/Florian Baumgarting (50407)",
            "fwnr": 413407
          }
        },
        "inzeit": "",
        "num1": "E241003575",
        "startzeit": "Fri, 25 Oct 2024 18:31:15 +0200",
        "status": "offen",
        "wgs84": {
          "lat": "48.0015",
          "lng": "13.5655"
        }
      }
    },
    {
      "einsatz": {
        "adresse": {
          "default": "Frankenburg am Hausruck",
          "earea": "Frankenburg am Hausruck",
          "ecompl": "",
          "efeanme": "",
          "emun": "Frankenburg am Hausruck",
          "estnum": ""
        },
        "alarmstufe": "0",
        "bezirk": {
          "id": 13,
          "text": "Vöcklabruck"
        },
        "cntfeuerwehren": 1,
        "einsatzart": "SELBST",
        "einsatzort": "VB - Frankenburg am Hausruck",
        "einsatzsubtyp": {
          "id": "TETRA-SELBST",
          "text": "Einsatz od. Einsatzübung"
        },
        "einsatztyp": {
          "id": "SELBST",
          "text": "Selbstständiger Einsatz"
        },
        "feuerwehren": {
          "413110": {
            "feuerwehr": "Feuerwehr/Florian Frankenburg am Hausruck (50110)"
          }
        },
        "feuerwehrenarray": {
          "0": {
            "fwname": "Feuerwehr/Florian Frankenburg am Hausruck (50110)",
            "fwnr": 413110
          }
        },
        "inzeit": "",
        "num1": "E241003444",
        "startzeit": "Thu, 24 Oct 2024 19:36:31 +0200",
        "status": "offen",
        "wgs84": {
          "lat": "48.0676",
          "lng": "13.4835"
        }
      }
    },
    {
      "einsatz": {
        "adresse": {
          "default": "St. Pantaleon",
          "earea": "St. Pantaleon",
          "ecompl": "",
          "efeanme": "",
          "emun": "St. Pantaleon",
          "estnum": ""
        },
        "alarmstufe": "0",
        "bezirk": {
          "id": 0,
          "text": "Braunau"
        },
        "cntfeuerwehren": 1,
        "einsatzart": "SELBST",
        "einsatzort": "BR - St. Pantaleon",
        "einsatzsubtyp": {
          "id": "TETRA-SELBST",
          "text": "Einsatz od. Einsatzübung"
        },
        "einsatztyp": {
          "id": "SELBST",
          "text": "Selbstständiger Einsatz"
        },
        "feuerwehren": {
          "400416": {
            "feuerwehr": "Feuerwehr/Florian Wildshut (33416)"
          }
        },
        "feuerwehrenarray": {
          "0": {
            "fwname": "Feuerwehr/Florian Wildshut (33416)",
            "fwnr": 400416
          }
        },
        "inzeit": "",
        "num1": "E241003417",
        "startzeit": "Thu, 24 Oct 2024 18:52:10 +0200",
        "status": "offen",
        "wgs84": {
          "lat": "48.0082",
          "lng": "12.8664"
        }
      }
    }
  ],
  "title": "laufend",
  "version": "1.3.1",
  "webext2": true
}
