{
  "cnt_einsaetze": 16,
  "cnt_feuerwehren": 16,
  "einsaetze": [
    {
      "einsatz": {
        "adresse": {
          "default": "Sierning",
          "earea": "Sierning",
          "ecompl": "",
          "efeanme": "",
          "emun": "Sierning",
          "estnum": ""
        },
        "alarmstufe": "0",
        "bezirk": {
          "id": 11,
          "text": "Steyr-Land"
        },
        "cntfeuerwehren": 1,
        "einsatzart": "SELBST",
        "einsatzort": "SE - Sierning",
        "einsatzsubtyp": {
          "id": "TETRA-SELBST",
          "text": "Einsatz od. Einsatzübung"
        },
        "einsatztyp": {
          "id": "SELBST",
          "text": "Selbstständiger Einsatz"
        },
        "feuerwehren": {
          "411211": {
            "feuerwehr": "Feuerwehr/Florian Pichlern (46211)"
          }
        },
        "feuerwehrenarray": {
          "0": {
            "fwname": "Feuerwehr/Florian Pichlern (46211)",
            "fwnr": 411211
          }
        },
        "inzeit": "",
        "num1": "E240500846",
        "startzeit": "Tue, 07 May 2024 19:04:10 +0200",
        "status": "offen",
        "wgs84": {
          "lat": "48.0275",
          "lng": "14.3229"
        }
      }
    },
    {
      "einsatz": {
        "adresse": {
          "default": "Pram",
          "earea": "Pram",
          "ecompl": "",
          "efeanme": "",
          "emun": "Pram",
          "estnum": ""
        },
        "alarmstufe": "0",
        "bezirk": {
          "id": 4,
          "text": "Grieskirchen"
        },
        "cntfeuerwehren": 1,
        "einsatzart": "SELBST",
        "einsatzort": "GR - Pram",
        "einsatzsubtyp": {
          "id": "TETRA-SELBST",
          "text": "Einsatz od. Einsatzübung"
        },
        "einsatztyp": {
          "id": "SELBST",
          "text": "Selbstständiger Einsatz"
        },
        "feuerwehren": {
          "404211": {
            "feuerwehr": "Feuerwehr/Florian Pram (37211)"
          }
        },
        "feuerwehrenarray": {
          "0": {
            "fwname": "Feuerwehr/Florian Pram (37211)",
            "fwnr": 404211
          }
        },
        "inzeit": "",
        "num1": "E240500843",
        "startzeit": "Tue, 07 May 2024 19:02:49 +0200",
        "status": "offen",
        "wgs84": {
          "lat": "48.2327",
          "lng": "13.6082"
        }
      }
    },
    {
      "einsatz": {
        "adresse": {
          "default": "Arbing",
          "earea": "Arbing",
          "ecompl": "",
          "efeanme": "",
          "emun": "Arbing",
          "estnum": ""
        },
        "alarmstufe": "0",
        "bezirk": {
          "id": 7,
          "text": "Perg"
        },
        "cntfeuerwehren": 1,
        "einsatzart": "SELBST",
        "einsatzort": "PE - Arbing",
        "einsatzsubtyp": {
          "id": "TETRA-SELBST",
          "text": "Einsatz od. Einsatzübung"
        },
        "einsatztyp": {
          "id": "SELBST",
          "text": "Selbstständiger Einsatz"
        },
        "feuerwehren": {
          "407302": {
            "feuerwehr": "Feuerwehr/Florian Arbing (42302)"
          }
        },
        "feuerwehrenarray": {
          "0": {
            "fwname": "Feuerwehr/Florian Arbing (42302)",
            "fwnr": 407302
          }
        },
        "inzeit": "",
        "num1": "E240500842",
        "startzeit": "Tue, 07 May 2024 19:02:29 +0200",
        "status": "offen",
        "wgs84": {
          "lat": "48.2301",
          "lng": "14.6991"
        }
      }
    },
    {
      "einsatz": {
        "adresse": {
          "default": "Mauthausen",
          "earea": "Mauthausen",
          "ecompl": "",
          "efeanme": "",
          "emun": "Mauthausen",
          "estnum": ""
        },
        "alarmstufe": "0",
        "bezirk": {
          "id": 7,
          "text": "Perg"
        },
        "cntfeuerwehren": 1,
        "einsatzart": "SELBST",
        "einsatzort": "PE - Mauthausen",
        "einsatzsubtyp": {
          "id": "TETRA-SELBST",
          "text": "Einsatz od. Einsatzübung"
        },
        "einsatztyp": {
          "id": "SELBST",
          "text": "Selbstständiger Einsatz"
        },
        "feuerwehren": {
          "407204": {
            "feuerwehr": "Feuerwehr/Florian Haid (PE) (42204)"
          }
        },
        "feuerwehrenarray": {
          "0": {
            "fwname": "Feuerwehr/Florian Haid (PE) (42204)",
            "fwnr": 407204
          }
        },
        "inzeit": "",
        "num1": "E240500841",
        "startzeit": "Tue, 07 May 2024 18:59:53 +0200",
        "status": "offen",
        "wgs84": {
          "lat": "48.2462",
          "lng": "14.5497"
        }
      }
    },
    {
      "einsatz": {
        "adresse": {
          "default": "Schwanenstadt",
          "earea": "Schwanenstadt",
          "ecompl": "",
          "efeanme": "",
          "emun": "Schwanenstadt",
          "estnum": ""
        },
        "alarmstufe": "0",
        "bezirk": {
          "id": 13,
          "text": "Vöcklabruck"
        },
        "cntfeuerwehren": 1,
        "einsatzart": "SELBST",
        "einsatzort": "VB - Schwanenstadt",
        "einsatzsubtyp": {
          "id": "TETRA-SELBST",
          "text": "Einsatz od. Einsatzübung"
        },
        "einsatztyp": {
          "id": "SELBST",
          "text": "Selbstständiger Einsatz"
        },
        "feuerwehren": {
          "413315": {
            "feuerwehr": "Feuerwehr/Florian Schwanenstadt (50315)"
          }
        },
        "feuerwehrenarray": {
          "0": {
            "fwname": "Feuerwehr/Florian Schwanenstadt (50315)",
            "fwnr": 413315
          }
        },
        "inzeit": "",
        "num1": "E240500840",
        "startzeit": "Tue, 07 May 2024 18:58:30 +0200",
        "status": "offen",
        "wgs84": {
          "lat": "48.0582",
          "lng": "13.7817"
        }
      }
    },
    {
      "einsatz": {
        "adresse": {
          "default": "Schwertberg",
          "earea": "Schwertberg",
          "ecompl": "",
          "efeanme": "",
          "emun": "Schwertberg",
          "estnum": ""
        },
        "alarmstufe": "0",
        "bezirk": {
          "id": 7,
          "text": "Perg"
        },
        "cntfeuerwehren": 1,
        "einsatzart": "SELBST",
        "einsatzort": "PE - Schwertberg",
        "einsatzsubtyp": {
          "id": "TETRA-SELBST",
          "text": "Einsatz od. Einsatzübung"
        },
        "einsatztyp": {
          "id": "SELBST",
          "text": "Selbstständiger Einsatz"
        },
        "feuerwehren": {
          "407216": {
            "feuerwehr": "Feuerwehr/Florian Schwertberg (42216)"
          }
        },
        "feuerwehrenarray": {
          "0": {
            "fwname": "Feuerwehr/Florian Schwertberg (42216)",
            "fwnr": 407216
          }
        },
        "inzeit": "",
        "num1": "E240500838",
        "startzeit": "Tue, 07 May 2024 18:57:38 +0200",
        "status": "offen",
        "wgs84": {
          "lat": "48.2734",
          "lng": "14.5798"
        }
      }
    },
    {
      "einsatz": {
        "adresse": {
          "default": "Luftenberg an der Donau",
          "earea": "Luftenberg an der Donau",
          "ecompl": "",
          "efeanme": "",
          "emun": "Luftenberg an der Donau",
          "estnum": ""
        },
        "alarmstufe": "0",
        "bezirk": {
          "id": 7,
          "text": "Perg"
        },
        "cntfeuerwehren": 1,
        "einsatzart": "SELBST",
        "einsatzort": "PE - Luftenberg an der Donau",
        "einsatzsubtyp": {
          "id": "TETRA-SELBST",
          "text": "Einsatz od. Einsatzübung"
        },
        "einsatztyp": {
          "id": "SELBST",
          "text": "Selbstständiger Einsatz"
        },
        "feuerwehren": {
          "407213": {
            "feuerwehr": "Feuerwehr/Florian Pürach (42213)"
          }
        },
        "feuerwehrenarray": {
          "0": {
            "fwname": "Feuerwehr/Florian Pürach (42213)",
            "fwnr": 407213
          }
        },
        "inzeit": "",
        "num1": "E240500837",
        "startzeit": "Tue, 07 May 2024 18:52:12 +0200",
        "status": "offen",
        "wgs84": {
          "lat": "48.285",
          "lng": "14.4201"
        }
      }
    },
    {
      "einsatz": {
        "adresse": {
          "default": "Ansfelden",
          "earea": "Ansfelden",
          "ecompl": "",
          "efeanme": "",
          "emun": "Ansfelden",
          "estnum": ""
        },
        "alarmstufe": "0",
        "bezirk": {
          "id": 6,
          "text": "Linz-Land"
        },
        "cntfeuerwehren": 1,
        "einsatzart": "SELBST",
        "einsatzort": "LL - Ansfelden",
        "einsatzsubtyp": {
          "id": "TETRA-SELBST",
          "text": "Einsatz od. Einsatzübung"
        },
        "einsatztyp": {
          "id": "SELBST",
          "text": "Selbstständiger Einsatz"
        },
        "feuerwehren": {
          "406213": {
            "feuerwehr": "Feuerwehr/Florian Nettingsdorf (39213)"
          }
        },
        "feuerwehrenarray": {
          "0": {
            "fwname": "Feuerwehr/Florian Nettingsdorf (39213)",
            "fwnr": 406213
          }
        },
        "inzeit": "",
        "num1": "E240500836",
        "startzeit": "Tue, 07 May 2024 18:48:37 +0200",
        "status": "offen",
        "wgs84": {
          "lat": "48.1873",
          "lng": "14.2562"
        }
      }
    },
    {
      "einsatz": {
        "adresse": {
          "default": "Natternbach",
          "earea": "Natternbach",
          "ecompl": "",
          "efeanme": "",
          "emun": "Natternbach",
          "estnum": ""
        },
        "alarmstufe": "0",
        "bezirk": {
          "id": 4,
          "text": "Grieskirchen"
        },
        "cntfeuerwehren": 1,
        "einsatzart": "SELBST",
        "einsatzort": "GR - Natternbach",
        "einsatzsubtyp": {
          "id": "TETRA-SELBST",
          "text": "Einsatz od. Einsatzübung"
        },
        "einsatztyp": {
          "id": "SELBST",
          "text": "Selbstständiger Einsatz"
        },
        "feuerwehren": {
          "404321": {
            "feuerwehr": "Feuerwehr/Florian Tal (37321)"
          }
        },
        "feuerwehrenarray": {
          "0": {
            "fwname": "Feuerwehr/Florian Tal (37321)",
            "fwnr": 404321
          }
        },
        "inzeit": "",
        "num1": "E240500835",
        "startzeit": "Tue, 07 May 2024 18:45:26 +0200",
        "status": "offen",
        "wgs84": {
          "lat": "48.4331",
          "lng": "13.7216"
        }
      }
    },
    {
      "einsatz": {
        "adresse": {
          "default": "Luftenberg an der Donau",
          "earea": "Luftenberg an der Donau",
          "ecompl": "",
          "efeanme": "",
          "emun": "Luftenberg an der Donau",
          "estnum": ""
        },
        "alarmstufe": "0",
        "bezirk": {
          "id": 7,
          "text": "Perg"
        },
        "cntfeuerwehren": 1,
        "einsatzart": "SELBST",
        "einsatzort": "PE - Luftenberg an der Donau",
        "einsatzsubtyp": {
          "id": "TETRA-SELBST",
          "text": "Einsatz od. Einsatzübung"
        },
        "einsatztyp": {
          "id": "SELBST",
          "text": "Selbstständiger Einsatz"
        },
        "feuerwehren": {
          "407207": {
            "feuerwehr": "Feuerwehr/Florian Langenstein (42207)"
          }
        },
        "feuerwehrenarray": {
          "0": {
            "fwname": "Feuerwehr/Florian Langenstein (42207)",
            "fwnr": 407207
          }
        },
        "inzeit": "",
        "num1": "E240500834",
        "startzeit": "Tue, 07 May 2024 18:44:24 +0200",
        "status": "offen",
        "wgs84": {
          "lat": "48.2735",
          "lng": "14.429"
        }
      }
    },
    {
      "einsatz": {
        "adresse": {
          "default": "Windischgarsten",
          "earea": "Windischgarsten",
          "ecompl": "",
          "efeanme": "",
          "emun": "Windischgarsten",
          "estnum": ""
        },
        "alarmstufe": "0",
        "bezirk": {
          "id": 5,
          "text": "Kirchdorf"
        },
        "cntfeuerwehren": 1,
        "einsatzart": "SELBST",
        "einsatzort": "KI - Windischgarsten",
        "einsatzsubtyp": {
          "id": "TETRA-SELBST",
          "text": "Einsatz od. Einsatzübung"
        },
        "einsatztyp": {
          "id": "SELBST",
          "text": "Selbstständiger Einsatz"
        },
        "feuerwehren": {
          "405405": {
            "feuerwehr": "Feuerwehr/Florian Windischgarsten (38405)"
          }
        },
        "feuerwehrenarray": {
          "0": {
            "fwname": "Feuerwehr/Florian Windischgarsten (38405)",
            "fwnr": 405405
          }
        },
        "inzeit": "",
        "num1": "E240500832",
        "startzeit": "Tue, 07 May 2024 18:35:09 +0200",
        "status": "offen",
        "wgs84": {
          "lat": "47.7196",
          "lng": "14.3204"
        }
      }
    },
    {
      "einsatz": {
        "adresse": {
          "default": "Sierning",
          "earea": "Sierning",
          "ecompl": "",
          "efeanme": "",
          "emun": "Sierning",
          "estnum": ""
        },
        "alarmstufe": "0",
        "bezirk": {
          "id": 11,
          "text": "Steyr-Land"
        },
        "cntfeuerwehren": 1,
        "einsatzart": "SELBST",
        "einsatzort": "SE - Sierning",
        "einsatzsubtyp": {
          "id": "TETRA-SELBST",
          "text": "Einsatz od. Einsatzübung"
        },
        "einsatztyp": {
          "id": "SELBST",
          "text": "Selbstständiger Einsatz"
        },
        "feuerwehren": {
          "411205": {
            "feuerwehr": "Feuerwehr/Florian Hilbern (46205)"
          }
        },
        "feuerwehrenarray": {
          "0": {
            "fwname": "Feuerwehr/Florian Hilbern (46205)",
            "fwnr": 411205
          }
        },
        "inzeit": "",
        "num1": "E240500831",
        "startzeit": "Tue, 07 May 2024 18:33:28 +0200",
        "status": "offen",
        "wgs84": {
          "lat": "48.0505",
          "lng": "14.2602"
        }
      }
    },
    {
      "einsatz": {
        "adresse": {
          "default": "Roitham am Traunfall",
          "earea": "Roitham am Traunfall",
          "ecompl": "",
          "efeanme": "",
          "emun": "Roitham am Traunfall",
          "estnum": ""
        },
        "alarmstufe": "0",
        "bezirk": {
          "id": 3,
          "text": "Gmunden"
        },
        "cntfeuerwehren": 1,
        "einsatzart": "SELBST",
        "einsatzort": "GM - Roitham am Traunfall",
        "einsatzsubtyp": {
          "id": "TETRA-SELBST",
          "text": "Einsatz od. Einsatzübung"
        },
        "einsatztyp": {
          "id": "SELBST",
          "text": "Selbstständiger Einsatz"
        },
        "feuerwehren": {
          "403213": {
            "feuerwehr": "Feuerwehr/Florian Lindach (36213)"
          }
        },
        "feuerwehrenarray": {
          "0": {
            "fwname": "Feuerwehr/Florian Lindach (36213)",
            "fwnr": 403213
          }
        },
        "inzeit": "",
        "num1": "E240500830",
        "startzeit": "Tue, 07 May 2024 18:07:43 +0200",
        "status": "offen",
        "wgs84": {
          "lat": null,
          "lng": null
        }
      }
    },
    {
      "einsatz": {
        "adresse": {
          "default": "Hargelsberg",
          "earea": "Hargelsberg",
          "ecompl": "",
          "efeanme": "",
          "emun": "Hargelsberg",
          "estnum": ""
        },
        "alarmstufe": "0",
        "bezirk": {
          "id": 6,
          "text": "Linz-Land"
        },
        "cntfeuerwehren": 1,
        "einsatzart": "SELBST",
        "einsatzort": "LL - Hargelsberg",
        "einsatzsubtyp": {
          "id": "TETRA-SELBST",
          "text": "Einsatz od. Einsatzübung"
        },
        "einsatztyp": {
          "id": "SELBST",
          "text": "Selbstständiger Einsatz"
        },
        "feuerwehren": {
          "406106": {
            "feuerwehr": "Feuerwehr/Florian Hofkirchen im Traunkreis (39106)"
          }
        },
        "feuerwehrenarray": {
          "0": {
            "fwname": "Feuerwehr/Florian Hofkirchen im Traunkreis (39106)",
            "fwnr": 406106
          }
        },
        "inzeit": "",
        "num1": "E240500829",
        "startzeit": "Tue, 07 May 2024 18:02:21 +0200",
        "status": "offen",
        "wgs84": {
          "lat": "48.1473",
          "lng": "14.4235"
        }
      }
    },
    {
      "einsatz": {
        "adresse": {
          "default": "Niederneukirchen",
          "earea": "Niederneukirchen",
          "ecompl": "",
          "efeanme": "",
          "emun": "Niederneukirchen",
          "estnum": ""
        },
        "alarmstufe": "0",
        "bezirk": {
          "id": 6,
          "text": "Linz-Land"
        },
        "cntfeuerwehren": 1,
        "einsatzart": "SELBST",
        "einsatzort": "LL - Niederneukirchen",
        "einsatzsubtyp": {
          "id": "TETRA-SELBST",
          "text": "Einsatz od. Einsatzübung"
        },
        "einsatztyp": {
          "id": "SELBST",
          "text": "Selbstständiger Einsatz"
        },
        "feuerwehren": {
          "406107": {
            "feuerwehr": "Feuerwehr/Florian Niederneukirchen (39107)"
          }
        },
        "feuerwehrenarray": {
          "0": {
            "fwname": "Feuerwehr/Florian Niederneukirchen (39107)",
            "fwnr": 406107
          }
        },
        "inzeit": "",
        "num1": "E240500817",
        "startzeit": "Tue, 07 May 2024 16:00:14 +0200",
        "status": "offen",
        "wgs84": {
          "lat": "48.1592",
          "lng": "14.3391"
        }
      }
    },
    {
      "einsatz": {
        "adresse": {
          "default": "Windhaag bei Freistadt",
          "earea": "Windhaag bei Freistadt",
          "ecompl": "",
          "efeanme": "",
          "emun": "Windhaag bei Freistadt",
          "estnum": ""
        },
        "alarmstufe": "0",
        "bezirk": {
          "id": 2,
          "text": "Freistadt"
        },
        "cntfeuerwehren": 1,
        "einsatzart": "SELBST",
        "einsatzort": "FR - Windhaag bei Freistadt",
        "einsatzsubtyp": {
          "id": "TETRA-SELBST",
          "text": "Einsatz od. Einsatzübung"
        },
        "einsatztyp": {
          "id": "SELBST",
          "text": "Selbstständiger Einsatz"
        },
        "feuerwehren": {
          "402422": {
            "feuerwehr": "Feuerwehr/Florian Windhaag bei Freistadt (35422)"
          }
        },
        "feuerwehrenarray": {
          "0": {
            "fwname": "Feuerwehr/Florian Windhaag bei Freistadt (35422)",
            "fwnr": 402422
          }
        },
        "inzeit": "",
        "num1": "E240500756",
        "startzeit": "Tue, 07 May 2024 08:10:35 +0200",
        "status": "offen",
        "wgs84": {
          "lat": "48.5861",
          "lng": "14.56"
        }
      }
    }
  ],
  "title": "laufend",
  "version": "1.3.1",
  "webext2": true
}
